web3client/.DS_Store
web3client/__init__.py
web3client/abi/compound_v2_cerc20.json
web3client/abi/compound_v2_ceth.json
web3client/abi/compound_v2_comptroller.json
web3client/abi/erc20.json
web3client/base_client.py
web3client/compound_v2_client.py
web3client/erc20_client.py
web3client/exceptions.py
web3client/helpers/__init__.py
web3client/helpers/debug.py
web3client/helpers/general.py
web3client/helpers/subscribe.py
web3client/helpers/tx.py
web3client/middlewares/.mypy_cache/.gitignore
web3client/middlewares/.mypy_cache/3.11/@plugins_snapshot.json
web3client/middlewares/.mypy_cache/3.11/__future__.data.json
web3client/middlewares/.mypy_cache/3.11/__future__.meta.json
web3client/middlewares/.mypy_cache/3.11/_ast.data.json
web3client/middlewares/.mypy_cache/3.11/_ast.meta.json
web3client/middlewares/.mypy_cache/3.11/_codecs.data.json
web3client/middlewares/.mypy_cache/3.11/_codecs.meta.json
web3client/middlewares/.mypy_cache/3.11/_collections_abc.data.json
web3client/middlewares/.mypy_cache/3.11/_collections_abc.meta.json
web3client/middlewares/.mypy_cache/3.11/_ctypes.data.json
web3client/middlewares/.mypy_cache/3.11/_ctypes.meta.json
web3client/middlewares/.mypy_cache/3.11/_decimal.data.json
web3client/middlewares/.mypy_cache/3.11/_decimal.meta.json
web3client/middlewares/.mypy_cache/3.11/_operator.data.json
web3client/middlewares/.mypy_cache/3.11/_operator.meta.json
web3client/middlewares/.mypy_cache/3.11/_random.data.json
web3client/middlewares/.mypy_cache/3.11/_random.meta.json
web3client/middlewares/.mypy_cache/3.11/_socket.data.json
web3client/middlewares/.mypy_cache/3.11/_socket.meta.json
web3client/middlewares/.mypy_cache/3.11/_thread.data.json
web3client/middlewares/.mypy_cache/3.11/_thread.meta.json
web3client/middlewares/.mypy_cache/3.11/_typeshed/__init__.data.json
web3client/middlewares/.mypy_cache/3.11/_typeshed/__init__.meta.json
web3client/middlewares/.mypy_cache/3.11/_warnings.data.json
web3client/middlewares/.mypy_cache/3.11/_warnings.meta.json
web3client-1.3.11.dist-info/entry_points.txt
web3client-1.3.11.dist-info/WHEEL
web3client-1.3.11.dist-info/METADATA
web3client-1.3.11.dist-info/licenses/LICENSE
web3client-1.3.11.dist-info/RECORD
