Metadata-Version: 2.1
Name: web3client
Version: 1.3.11
Summary: Batteries-included client to interact with blockchains and smart contracts
License: MIT
Keywords: web3,blockchain,ethereum,evm
Author-email: coccoinomane <coccoinomane@gmail.com>
Requires-Python: >=3.9
Requires-Dist: eth-typing>=2.3.0
Requires-Dist: pre-commit>=2.21.0
Requires-Dist: py-evm>=0.7.0a4
Requires-Dist: setuptools>=67.2.0
Requires-Dist: typing-extensions>=4.4.0
Requires-Dist: web3>=6.0.0
Requires-Dist: websockets>=10.0
Project-URL: homepage, https://github.com/coccoinomane/web3client
Project-URL: repository, https://github.com/coccoinomane/web3client
